pyautoreloadserver/__init__.py
pyautoreloadserver/__main__.py
pyautoreloadserver/cli.py
pyautoreloadserver/pyautoreloadserver.py
tests/__init__.py
tests/client.py
tests/test_auto_reload_http_server.py
pyautoreloadserver-0.0.2.dist-info/LICENSE
pyautoreloadserver-0.0.2.dist-info/METADATA
pyautoreloadserver-0.0.2.dist-info/WHEEL
pyautoreloadserver-0.0.2.dist-info/entry_points.txt
pyautoreloadserver-0.0.2.dist-info/top_level.txt
pyautoreloadserver-0.0.2.dist-info/RECORD
